pygindex/__init__.py
pygindex/cli.py
pygindex/client.py
pygindex/models.py
pygindex/utils.py
pygindex/templates/cli_get_account.j2
pygindex/templates/cli_get_instrument.j2
pygindex/templates/cli_get_positions.j2
pygindex/templates/cli_search_instrument.j2
pygindex-0.2.0.dist-info/entry_points.txt
pygindex-0.2.0.dist-info/LICENSE
pygindex-0.2.0.dist-info/WHEEL
pygindex-0.2.0.dist-info/METADATA
pygindex-0.2.0.dist-info/RECORD
