Metadata-Version: 2.1
Name: pygindex
Version: 0.2.0
Summary: PyGIndex - Python library/framework
Author-email: Rytis Sileika <rts.pub@pulegium.eu>
Classifier: Development Status :: 3 - Alpha
Classifier: License :: OSI Approved :: GNU General Public License v3 or later (GPLv3+)
Classifier: Operating System :: POSIX
Classifier: Programming Language :: Python :: 3
Classifier: Programming Language :: Python :: 3 :: Only
Classifier: Programming Language :: Python :: 3.9
Classifier: Programming Language :: Python :: 3.10
Classifier: Topic :: Software Development :: Libraries
Classifier: Topic :: Office/Business :: Financial
Classifier: Intended Audience :: Developers
Classifier: Intended Audience :: Financial and Insurance Industry
Requires-Dist: requests
Requires-Dist: PyYAML
Requires-Dist: arrow
Project-URL: documentation, https://pygindex.readthedocs.io/en/latest/
Project-URL: source, https://github.com/rytis/pygindex/
